limesqueezer/_API.py
limesqueezer/__init__.py
limesqueezer/__main__.py
limesqueezer/auxiliaries.py
limesqueezer/cli.py
limesqueezer/errorfunctions.py
limesqueezer/models.py
limesqueezer/root.py
limesqueezer/reference/API.py
limesqueezer/reference/__init__.py
limesqueezer-1.0.13.dist-info/LICENSE.txt
limesqueezer-1.0.13.dist-info/METADATA
limesqueezer-1.0.13.dist-info/WHEEL
limesqueezer-1.0.13.dist-info/entry_points.txt
limesqueezer-1.0.13.dist-info/top_level.txt
limesqueezer-1.0.13.dist-info/RECORD
