Metadata-Version: 2.1
Name: limesqueezer
Version: 1.0.13
Summary: Lossy compression with controlled error tolerance for smooth data series
Author: Limespy
Project-URL: Homepage, https://github.com/Limespy/limesqueezer
Project-URL: Changelog, https://github.com/Limespy/limesqueezer/blob/main/README.md#Changelog
Project-URL: Issue Tracker, https://github.com/Limespy/limesqueezer/issues
Classifier: Development Status :: 3 - Alpha
Classifier: License :: OSI Approved :: MIT License
Classifier: Operating System :: Unix
Classifier: Operating System :: POSIX
Classifier: Operating System :: Microsoft :: Windows
Classifier: Programming Language :: Python :: 3
Classifier: Programming Language :: Python :: 3 :: Only
Classifier: Programming Language :: Python :: 3.10
Classifier: Programming Language :: Python :: 3.11
Classifier: Programming Language :: Python :: 3.12
Classifier: Topic :: Scientific/Engineering
Classifier: Topic :: System :: Archiving :: Compression
Classifier: Topic :: Utilities
Requires-Python: >=3.10
License-File: LICENSE.txt
Requires-Dist: limedev >=0.6.1
Requires-Dist: matplotlib >=3.5
Requires-Dist: numba >=0.55.2
Requires-Dist: numpy >=1.22
Requires-Dist: scipy >=1.8
Provides-Extra: build
Requires-Dist: limedev[package] >=0.6.1 ; extra == 'build'
Provides-Extra: dev
Requires-Dist: limedev[package,readme,test] >=0.6.1 ; extra == 'dev'
Requires-Dist: pre-commit >=3.6.0 ; extra == 'dev'
Requires-Dist: tox >=4.5.1 ; extra == 'dev'
